ctms/utils/__init__.py
ctms/utils/clib.dll
ctms/utils/clib.py
ctms/utils/clib.pyi
ctms/utils/dataops.py
ctms/utils/futils.py
ctms/utils/gitops.py
ctms/utils/numops.py
ctms_utils-0.3.1.dist-info/METADATA
ctms_utils-0.3.1.dist-info/WHEEL
ctms_utils-0.3.1.dist-info/top_level.txt
ctms_utils-0.3.1.dist-info/RECORD
